Hamhoush/__init__.py
Hamhoush/api.py
HamhoushSDK-0.1.dist-info/METADATA
HamhoushSDK-0.1.dist-info/WHEEL
HamhoushSDK-0.1.dist-info/top_level.txt
HamhoushSDK-0.1.dist-info/RECORD
