Metadata-Version: 2.1
Name: HamhoushSDK
Version: 0.1
Summary: hamhoush platform sdk
Author: Smilinno
Requires-Dist: numpy
Requires-Dist: requests
